{
  "project_info": {
    "project_number": "97604381182",
    "project_id": "fir-1-27d6a",
    "storage_bucket": "fir-1-27d6a.firebasestorage.app"
  },
  "client": [
    {
      "client_info": {
        "mobilesdk_app_id": "1:97604381182:ios:e3aad6a4010d95a285f8af",
        "android_client_info": {
          "package_name": "com.company.firebase3"
        }
      },
      "api_key": [
        {
          "current_key": "AIzaSyBNnqUAQanXn_gwfEF8Cz34AtuDv6SlyBc"
        }
      ],
      "services": {
        "analytics_service": {
          "status": 0
        },
        "appinvite_service": {
          "status": 1
        }
      }
    }
  ],
  "configuration_version": "1"
}